golemgpt/__main__.py
golemgpt/settings.py
golemgpt/actions/__init__.py
golemgpt/actions/ask_google.py
golemgpt/actions/ask_human_input.py
golemgpt/actions/delegate_job.py
golemgpt/actions/explain.py
golemgpt/actions/finish_job.py
golemgpt/actions/get_local_date.py
golemgpt/actions/get_os_details.py
golemgpt/actions/http_download.py
golemgpt/actions/read_file.py
golemgpt/actions/reject_job.py
golemgpt/actions/run_script.py
golemgpt/actions/search_images_via_bing.py
golemgpt/actions/search_text_via_bing.py
golemgpt/actions/summarize_file.py
golemgpt/actions/write_file.py
golemgpt/codex/__init__.py
golemgpt/codex/base.py
golemgpt/codex/reasonable.py
golemgpt/codex/unaware.py
golemgpt/cognitron/__init__.py
golemgpt/cognitron/base.py
golemgpt/cognitron/openai.py
golemgpt/cognitron/openai_plain.py
golemgpt/golems/__init__.py
golemgpt/golems/general.py
golemgpt/lexicon/__init__.py
golemgpt/lexicon/base.py
golemgpt/lexicon/general.py
golemgpt/lexicon/prompts.py
golemgpt/memory/__init__.py
golemgpt/memory/base.py
golemgpt/memory/localfiles.py
golemgpt/runners/__init__.py
golemgpt/runners/alwaysask.py
golemgpt/runners/justdo.py
golemgpt/utils/__init__.py
golemgpt/utils/console.py
golemgpt/utils/environ.py
golemgpt/utils/exceptions.py
golemgpt/utils/http.py
golemgpt/utils/misc.py
golemgpt/utils/images/__main__.py
golemgpt/utils/images/prompt.py
golemgpt/utils/images/settings.py
golem_gpt-0.2.1.dist-info/LICENSE
golem_gpt-0.2.1.dist-info/METADATA
golem_gpt-0.2.1.dist-info/WHEEL
golem_gpt-0.2.1.dist-info/top_level.txt
golem_gpt-0.2.1.dist-info/RECORD
