Metadata-Version: 2.1
Name: golem-gpt
Version: 0.2.1
Summary: Framework for building actionable agents on top of GPT-4
Author-email: Alexey Kinev <rudy@05bit.com>
Project-URL: Homepage, https://github.com/Dingolytics/golem-gpt
Project-URL: Bug Tracker, https://github.com/Dingolytics/golem-gpt/issues
Classifier: Development Status :: 3 - Alpha
Classifier: Programming Language :: Python :: 3
Classifier: License :: OSI Approved :: Apache Software License
Classifier: Operating System :: OS Independent
Requires-Python: >=3.8
License-File: LICENSE
Requires-Dist: pydantic ==1.10.7
Requires-Dist: python-dotenv ==1.0.0
Requires-Dist: termcolor ==2.2.0
Requires-Dist: typing-extensions ==4.12.2
Requires-Dist: urllib3 ==1.26.15
